smartdoor/__init__.py
smartdoor/default_config.toml
smartdoor/logging.conf
smartdoor/pigpio.service
smartdoor/smartdoor.py
smartdoor/smartdoor.service
smartdoor/core/__init__.py
smartdoor/core/authenticate.py
smartdoor/core/smartlock.py
smartdoor-2.0.1.dist-info/entry_points.txt
smartdoor-2.0.1.dist-info/LICENSE.md
smartdoor-2.0.1.dist-info/WHEEL
smartdoor-2.0.1.dist-info/METADATA
smartdoor-2.0.1.dist-info/RECORD
