Metadata-Version: 2.1
Name: smartdoor
Version: 2.0.1
Summary: Smartdoor system including NFC card detecting, key locking/unlocking, turning LED on/off, etc.
Author-email: Koyo Munechika <munechika.koyo@torus.nr.titech.ac.jp>
Maintainer-email: Koyo Munechika <munechika.koyo@torus.nr.titech.ac.jp>
Requires-Python: >=3.9
Classifier: Development Status :: 5 - Production/Stable
Classifier: Environment :: Console
Classifier: Intended Audience :: End Users/Desktop
Classifier: License :: OSI Approved :: BSD License
Classifier: Natural Language :: English
Classifier: Operating System :: POSIX :: Linux
Classifier: Programming Language :: Python :: 3.9
Classifier: Programming Language :: Python :: 3.10
Classifier: Programming Language :: Python :: 3.11
Classifier: Topic :: Home Automation
Classifier: Topic :: Security
Requires-Dist: rich-click
Requires-Dist: requests
Requires-Dist: nfcpy
Requires-Dist: gpiozero
Requires-Dist: tomli; python_version < "3.11"
Requires-Dist: flit ; extra == "dev"
Requires-Dist: pytest ; extra == "dev"
Requires-Dist: black ; extra == "dev"
Requires-Dist: ruff ; extra == "dev"
Requires-Dist: mypy ; extra == "dev"
Requires-Dist: pre-commit ; extra == "dev"
Project-URL: Home, https://github.com/munechika-koyo/smartdoor
Provides-Extra: dev
